sta_converter/__init__.py
sta_converter/converter.py
sta_converter-0.1.2.dist-info/METADATA
sta_converter-0.1.2.dist-info/WHEEL
sta_converter-0.1.2.dist-info/entry_points.txt
sta_converter-0.1.2.dist-info/RECORD
