Metadata-Version: 2.1
Name: sta-converter
Version: 0.1.2
Summary: A CLI tool for converting .sta (MT940) files to CSV and merging CSV files.
Home-page: https://github.com/bravelab/sta-converter
License: MIT
Keywords: mt940,sta,bank statement,converter,csv
Author: Mariusz Smenżyk
Author-email: mariusz@bravelab.io
Requires-Python: >=3.9,<4.0
Classifier: License :: OSI Approved :: MIT License
Classifier: Programming Language :: Python :: 3
Classifier: Programming Language :: Python :: 3.9
Classifier: Programming Language :: Python :: 3.10
Classifier: Programming Language :: Python :: 3.11
Classifier: Programming Language :: Python :: 3.12
Requires-Dist: click (>=8.1.7,<9.0.0)
Requires-Dist: mt940 (>=0.6.0,<0.7.0)
Project-URL: Repository, https://github.com/bravelab/sta-converter
